{
    "028f869d-cf12-444a-aefc-62f8b6294acd": [
        196,
        442,
        27,
        62,
        126,
        36
    ],
    "0594f5fe-3bef-4642-8bb7-9ac356f44acb": [
        83,
        392,
        94,
        89,
        121,
        97,
        716
    ],
    "07bd0dbc-5591-4b1a-ba75-fb7a84c28986": [
        61,
        389,
        249,
        244,
        503,
        163,
        190,
        788
    ],
    "095f8e2c-4c6b-45d3-983b-c0a836cd1d4e": [
        212,
        221,
        185,
        76,
        57,
        547,
        181,
        1008
    ],
    "0d4caeec-0d56-4074-a2df-4bf5012d1c19": [
        295,
        616,
        94,
        301,
        84,
        462,
        126,
        1261
    ],
    "11d555f4-f5e4-4f64-a0cd-f89f2b29553d": [
        77,
        165,
        41,
        89,
        118,
        365
    ],
    "139dce53-526b-4950-83cc-1ce060739e3e": [
        231,
        267,
        164,
        273,
        538,
        176,
        865
    ],
    "15f0ac31-1302-40eb-ba03-b486561cfd2b": [
        334,
        191,
        228,
        376,
        166,
        189,
        1211
    ],
    "1809810f-858f-468c-b9a4-bbcf0523bcdb": [
        81,
        60,
        93,
        180,
        222,
        287,
        262,
        723
    ],
    "180eb804-cb97-4406-90e8-3e7a09f9c053": [
        264,
        464,
        157,
        92,
        447,
        334,
        922
    ],
    "1814b1e7-c4eb-4450-b1f0-e610c6867ad1": [
        114,
        116,
        236,
        94,
        291,
        327,
        275,
        1516
    ],
    "1b036ecb-5907-4257-a3eb-f564536938b2": [
        45,
        168,
        133,
        174,
        173,
        185,
        890
    ],
    "1b9af03a-f1c8-4a44-a8af-1145c839107b": [
        112,
        45,
        110,
        49,
        48,
        293,
        126,
        696
    ],
    "1fa4c466-c4d5-4687-8768-c48b51d3a2bd": [
        360,
        132,
        114,
        382,
        88,
        260,
        362,
        1574
    ],
    "2085249e-2875-4d5b-a538-0b01f43880fa": [
        463,
        372,
        186,
        271,
        813,
        434,
        1500
    ],
    "2792182e-9171-4d23-a5c2-6c1e5e65d5ad": [
        118,
        172,
        119,
        51,
        110,
        121,
        85,
        677
    ],
    "2c2254a1-01fc-498c-9754-f9022c082640": [
        287,
        628,
        384,
        476,
        620,
        1173
    ],
    "2d97b29f-39b8-405c-b536-7ca08a060e8b": [
        39,
        68,
        68,
        63,
        207,
        102,
        124,
        875
    ],
    "2e536c84-7daa-4e12-b307-4e210953b7ea": [
        135,
        113,
        81,
        35,
        78,
        196,
        510
    ],
    "3250a893-1fe5-49de-9bc9-4779dfe68c13": [
        126,
        70,
        59,
        83,
        210,
        156,
        0
    ],
    "34418c58-f3e9-4dfd-94fe-de4dec288206": [
        65,
        307,
        81,
        58,
        342,
        278,
        409,
        920
    ],
    "391ae05a-aaea-4445-ba16-02d78ea61b70": [
        383,
        151,
        171,
        261,
        185,
        104,
        235,
        668
    ],
    "3a7772b5-2338-4428-b688-a895d4911cec": [
        200,
        44,
        127,
        213,
        100,
        124,
        119,
        384
    ],
    "3b13bb6b-933c-4fac-a920-5d63c2537cfa": [
        99,
        442,
        298,
        544,
        450,
        99,
        73,
        1522
    ],
    "3bd075d6-b91b-4f60-9138-c33feff56d2c": [
        139,
        478,
        132,
        565,
        227,
        448,
        477,
        767
    ],
    "3c54ff28-8df5-46af-9a92-f6485d99aab6": [
        83,
        336,
        524,
        377,
        186,
        99,
        770
    ],
    "3c7a897a-7c1d-4208-868c-a5e3b1382245": [
        136,
        331,
        77,
        24,
        41,
        108,
        105,
        620
    ],
    "3d355114-3f2e-4ff0-8bca-f3ca8b2f7464": [
        267,
        259,
        213,
        164,
        87,
        127,
        475
    ],
    "3f01371c-5cc3-4b78-a05b-2211637ac21c": [
        214,
        99,
        364,
        77,
        141,
        428,
        199
    ],
    "3f2b7591-7433-4138-b716-e30c1c96fcd7": [
        100,
        180,
        168,
        111,
        118,
        245,
        324
    ],
    "3f5bfecb-272d-4535-a0f3-e2d083b80a5b": [
        66,
        101,
        31,
        87,
        132,
        131,
        30,
        331
    ],
    "3f96869b-6cc1-448e-ad1d-07d74985ffeb": [
        60,
        116,
        140,
        223,
        179,
        313,
        259
    ],
    "416cc7ff-3394-44af-b09c-4af4b3dc0f30": [
        14,
        178,
        145,
        188,
        215,
        36,
        644
    ],
    "464105a7-8c06-4b22-9f4d-0996f51baa47": [
        103,
        361,
        121,
        323,
        478,
        104,
        112,
        1801
    ],
    "49d3315e-05e3-47a3-981a-12e39c75d4e2": [
        123,
        234,
        243,
        129,
        163,
        136,
        277
    ],
    "4b0f71c3-126f-41a3-a304-0c587a6de2a4": [
        305,
        180,
        168,
        78,
        186,
        249,
        181,
        691
    ],
    "4d5061ed-8982-49b1-b4c1-5bb78977e931": [
        48,
        97,
        80,
        72,
        113,
        196,
        126,
        596
    ],
    "53160b89-5ba2-4239-a4ff-f9911466166f": [
        52,
        438,
        176,
        172,
        286,
        67,
        397,
        802
    ],
    "572252a2-ab55-4029-a99a-7fd786fd963f": [
        120,
        210,
        170,
        12,
        183,
        115,
        52,
        187
    ],
    "577de68d-dc5d-4c5c-a7ae-948a6645fb1e": [
        274,
        403,
        256,
        85,
        502,
        239,
        1531
    ],
    "5904e50b-711c-4683-882d-afdbe40125ad": [
        336,
        441,
        561,
        323,
        472,
        1157
    ],
    "5b5158f4-bc3d-4c99-84fe-c8c99a840fac": [
        180,
        370,
        355,
        332,
        253,
        539,
        998
    ],
    "63277108-b3f6-439e-a6e2-09515f909318": [
        194,
        367,
        300,
        95,
        325,
        431,
        227,
        886
    ],
    "653caf7c-6c7f-4e07-92d1-07d7a7df4a70": [
        606,
        168,
        173,
        711,
        679,
        221,
        202,
        1138
    ],
    "66a3c1da-ac08-4ae0-8288-6aa3df78f5ae": [
        332,
        360,
        220,
        254,
        337,
        433
    ],
    "6771157a-1f77-4752-96d1-91215c77efb5": [
        280,
        317,
        106,
        554,
        84,
        81,
        237,
        1374
    ],
    "6b41030e-adfb-48ba-964d-63f3fb655c20": [
        102,
        127,
        280,
        45,
        176,
        129,
        253,
        787
    ],
    "6c74f8b6-b9f4-44b6-83fd-2db50c0a1d7f": [
        128,
        124,
        144,
        95,
        120,
        628
    ],
    "6cdb31f4-3732-435a-9a20-f90807d19cdf": [
        206,
        264,
        278,
        234,
        68,
        101,
        80,
        254
    ],
    "6da0587d-c0df-4074-9659-ab5f531ea32e": [
        164,
        288,
        125,
        165,
        43,
        153,
        75,
        425
    ],
    "6f503e5f-09c4-42ad-90a8-f64acaee184f": [
        255,
        59,
        90,
        115,
        50,
        137,
        103,
        748
    ],
    "6f8ff031-2968-4f0a-82bc-55d1bbcea580": [
        103,
        459,
        681,
        96,
        408,
        278,
        367,
        1290
    ],
    "71df972f-32d4-460a-bea9-eed041325afa": [
        158,
        105,
        86,
        209,
        100,
        56,
        0
    ],
    "74284cd2-0993-4b1c-ba38-bd0e161104a2": [
        69,
        107,
        85,
        75,
        76,
        173,
        25,
        0
    ],
    "760cda2b-cda9-4540-a967-cb1369f7faf2": [
        186,
        252,
        268,
        219,
        221,
        144,
        731
    ],
    "7bf77ae2-059c-48cd-ba8d-ebdb40b42d48": [
        197,
        171,
        87,
        293,
        171,
        360,
        106,
        652
    ],
    "7c45b41a-8972-40ca-92af-a7463d45785b": [
        171,
        421,
        317,
        189,
        415,
        209,
        402,
        1691
    ],
    "7ed4a7df-adab-4320-9ca4-f8cd1f51cb30": [
        152,
        315,
        44,
        91,
        118,
        161,
        337,
        470
    ],
    "80a2dd36-56bb-4d6d-a16b-5887a2732e17": [
        258,
        138,
        60,
        78,
        51,
        44,
        180,
        321
    ],
    "866e2f2f-2906-42ba-911e-1d6478c648a4": [
        14,
        228,
        105,
        193,
        271,
        322,
        180
    ],
    "8cc5d294-2b7c-476d-a277-754e8087254a": [
        92,
        139,
        72,
        42,
        134,
        119,
        0
    ],
    "8cf18673-5f91-4d98-bf95-efe5c9547d17": [
        157,
        244,
        158,
        166,
        171,
        204,
        37,
        380
    ],
    "8e301e72-344d-4331-89bc-4dc1edca20fe": [
        139,
        277,
        145,
        152,
        303,
        747
    ],
    "8fd69250-71ad-4b24-9dca-0658d6eb95fc": [
        80,
        229,
        130,
        176,
        144,
        188,
        943
    ],
    "91300316-873e-4693-b740-b4c328275be0": [
        174,
        84,
        33,
        22,
        60,
        99,
        51,
        0
    ],
    "921d9fca-67ce-4f9f-8153-06e588b2817c": [
        164,
        168,
        367,
        194,
        504,
        326,
        180,
        1194
    ],
    "95bd926c-7fdd-4b77-a138-543a087193e9": [
        55,
        239,
        53,
        302,
        74,
        246,
        819
    ],
    "a34205f6-2279-4782-b072-acbf2f366920": [
        268,
        285,
        592,
        143,
        152,
        153,
        366,
        1563
    ],
    "a34730de-4f8f-47dc-b2c3-b26449cf828a": [
        48,
        190,
        123,
        148,
        48,
        200,
        782
    ],
    "a40ee84f-6a54-44a7-a021-d37588c0324d": [
        170,
        151,
        258,
        346,
        489,
        369,
        129,
        405
    ],
    "a6b0f005-b108-4171-b937-8d236c4c8f0c": [
        76,
        302,
        197,
        102,
        353,
        278,
        169,
        220
    ],
    "a7bacaf0-6881-4d73-8d3d-85b093a44786": [
        157,
        211,
        136,
        219,
        364,
        511,
        142,
        436
    ],
    "a8a35ead-e919-4cfc-ad3d-6ec70f8668b2": [
        320,
        306,
        286,
        356,
        76,
        220,
        186,
        863
    ],
    "aa3d5a2a-06b4-45fd-954e-c1f50232d127": [
        485,
        391,
        298,
        318,
        357,
        300,
        1372
    ],
    "acbd45bd-1ee2-4eae-94af-804faff1aefb": [
        69,
        560,
        121,
        264,
        415,
        69,
        1288
    ],
    "b2a258e0-7d2a-4cbd-8fbe-6102cb280aee": [
        143,
        205,
        466,
        91,
        94,
        14,
        371,
        1124
    ],
    "b2e3d4d7-9f94-434f-add3-edf3bb36dd53": [
        598,
        125,
        107,
        410,
        99,
        247,
        219,
        1401
    ],
    "b3901ef7-2dd2-4ce3-867e-92bc3f21e075": [
        43,
        193,
        101,
        68,
        289,
        33,
        258
    ],
    "b438b22c-f2db-44e8-8176-85765361ca04": [
        273,
        255,
        260,
        601,
        371,
        224,
        1716
    ],
    "b49b1b8b-eaf3-4ff7-b118-b07cc3939031": [
        326,
        237,
        177,
        155,
        101,
        274,
        424,
        1200
    ],
    "b4e5422e-374d-473d-bd20-f87d3095980b": [
        165,
        71,
        168,
        299,
        85,
        597,
        158,
        618
    ],
    "b50e9b8e-4457-4352-b682-7207abc27332": [
        153,
        166,
        112,
        47,
        105,
        174,
        85,
        752
    ],
    "b6690a80-1a74-40f1-bccd-7248c272121c": [
        69,
        80,
        170,
        120,
        62,
        101,
        388
    ],
    "b7674ce3-6caf-443a-b076-b6ae35f421a2": [
        178,
        180,
        280,
        113,
        147,
        116,
        264
    ],
    "ba0e88c5-6c7c-4425-b8b7-ff505eac17c5": [
        67,
        211,
        598,
        394,
        211,
        503,
        287,
        1867
    ],
    "ba63bdf2-e7cf-441e-9647-362eb298248d": [
        68,
        227,
        211,
        314,
        76,
        225,
        658
    ],
    "bd9afcb8-af8a-4223-8bee-a077576acb95": [
        188,
        83,
        73,
        300,
        256,
        51,
        493
    ],
    "bdfcc19e-d999-4983-a565-4b5254352b74": [
        147,
        171,
        35,
        75,
        60,
        128,
        144,
        34
    ],
    "bf2a3ac4-6958-4c74-8c25-413cbc5c36ec": [
        63,
        144,
        199,
        92,
        328,
        149,
        251,
        783
    ],
    "c41d09dc-05e0-45a0-b16e-02c7bde95e81": [
        80,
        116,
        22,
        72,
        37,
        193,
        356
    ],
    "c7ebc04c-0cd5-47a6-a086-9591a0083c61": [
        78,
        183,
        121,
        46,
        126,
        38,
        119
    ],
    "c808ccff-5938-4794-8df8-950448318d4e": [
        564,
        784,
        37,
        357,
        182,
        1394
    ],
    "c8c3eda7-92ec-4880-a6cf-4b26bb1f3815": [
        556,
        474,
        312,
        190,
        86,
        95,
        741
    ],
    "ca0f16c9-a47c-462b-a46f-43071a9bdb4d": [
        59,
        216,
        174,
        232,
        75,
        180,
        558
    ],
    "cabb2bd6-d503-4deb-bbdd-dcb27f0406fd": [
        324,
        113,
        570,
        171,
        342,
        70,
        134,
        1002
    ],
    "cc2380bb-531d-4b95-ae84-5182d714b6d6": [
        511,
        468,
        103,
        230,
        147,
        291,
        311,
        1207
    ],
    "cd732919-eb72-4ceb-9f5f-6e7ee25426ed": [
        184,
        183,
        161,
        106,
        63,
        27,
        938
    ],
    "ce54c6c9-6b00-4cf4-96e3-48e4b90585f7": [
        158,
        96,
        158,
        456,
        111,
        257,
        273,
        632
    ],
    "d0497e69-0af6-4295-8648-26afe141f8a0": [
        225,
        91,
        254,
        167,
        510,
        184,
        877
    ],
    "dab1eb5f-be8e-45cb-962a-3f5bed969e12": [
        131,
        53,
        50,
        57,
        300,
        111,
        207,
        740
    ],
    "de51fa6c-ee7b-4430-8dcd-52b0046c00bc": [
        92,
        32,
        192,
        163,
        115,
        108,
        42,
        794
    ],
    "e0a42643-3f2e-429c-bc00-c8332dc641d1": [
        175,
        85,
        227,
        110,
        60,
        71,
        209,
        840
    ],
    "e207a185-3ea3-4720-aed1-8064a3cb9b9f": [
        624,
        192,
        236,
        309,
        88,
        481,
        1517
    ],
    "e470e71c-6473-407f-bd14-12c66828b5d5": [
        126,
        187,
        125,
        570,
        322,
        94,
        241,
        2337
    ],
    "e856fa7c-da3c-49b4-a187-dbdc2d763e1f": [
        167,
        215,
        432,
        86,
        158,
        56,
        168,
        936
    ],
    "e9801980-cc94-488a-a8fc-516aab14ce1f": [
        73,
        108,
        281,
        182,
        61,
        347,
        166,
        356
    ],
    "ea09d5b8-22f5-4c75-a838-80c63ba84ff2": [
        223,
        231,
        606,
        155,
        542,
        140,
        1700
    ],
    "ea8eb1b0-dfff-495d-b569-9053aa8f4a8f": [
        587,
        133,
        21,
        278,
        245,
        276,
        252,
        796
    ],
    "ed709c3a-29f6-45f3-a63b-f1f4283d3d89": [
        284,
        86,
        300,
        93,
        242,
        189,
        321,
        604
    ],
    "f4c92f48-1045-49db-9ad5-c5aee0f650cc": [
        268,
        206,
        53,
        299,
        719,
        213,
        193,
        744
    ],
    "f66c6907-aa30-4dc3-8752-fa4b6d926e14": [
        45,
        71,
        124,
        168,
        332,
        98,
        408
    ],
    "f7221fe4-3eac-42f2-937a-1dacbbe72395": [
        218,
        395,
        463,
        357,
        368,
        367,
        1346
    ],
    "f8085173-8cbf-4c15-a9e8-713c40539bdd": [
        176,
        328,
        166,
        218,
        294,
        293,
        115,
        808
    ],
    "f83f95e7-1200-4dcd-a620-29694858190b": [
        113,
        47,
        196,
        188,
        59,
        181,
        146,
        271
    ],
    "fce13b53-ae50-47b2-b70e-1de66f31a8bf": [
        44,
        349,
        139,
        42,
        122,
        74,
        99,
        677
    ],
    "fdb670f7-dd7e-4222-8f5e-e3c6a8fccff4": [
        70,
        653,
        65,
        211,
        514,
        255,
        1716
    ]
}